rest_email_auth/__init__.py
rest_email_auth/admin.py
rest_email_auth/app_settings.py
rest_email_auth/apps.py
rest_email_auth/authentication.py
rest_email_auth/factories.py
rest_email_auth/generics.py
rest_email_auth/management/__init__.py
rest_email_auth/management/commands/__init__.py
rest_email_auth/management/commands/cleanemailconfirmations.py
rest_email_auth/managers.py
rest_email_auth/migrations/0001_initial.py
rest_email_auth/migrations/0002_emailconfirmation.py
rest_email_auth/migrations/0003_unique_emails.py
rest_email_auth/migrations/0004_emailaddress_is_primary.py
rest_email_auth/migrations/0005_passwordresettoken.py
rest_email_auth/migrations/0006_fix_primary_emails.py
rest_email_auth/migrations/__init__.py
rest_email_auth/models.py
rest_email_auth/serializers.py
rest_email_auth/signals.py
rest_email_auth/templates/rest_email_auth/emails/duplicate-email.txt
rest_email_auth/templates/rest_email_auth/emails/reset-password.txt
rest_email_auth/templates/rest_email_auth/emails/verify-email.txt
rest_email_auth/tests/__init__.py
rest_email_auth/tests/authentication/__init__.py
rest_email_auth/tests/authentication/conftest.py
rest_email_auth/tests/authentication/test_base_backend.py
rest_email_auth/tests/authentication/test_verified_email_backend.py
rest_email_auth/tests/conftest.py
rest_email_auth/tests/generics/__init__.py
rest_email_auth/tests/generics/test_serializer_save_view.py
rest_email_auth/tests/management/__init__.py
rest_email_auth/tests/management/commands/__init__.py
rest_email_auth/tests/management/commands/test_cleanemailconfirmations_command.py
rest_email_auth/tests/models/__init__.py
rest_email_auth/tests/models/test_email_address_model.py
rest_email_auth/tests/models/test_email_confirmation_model.py
rest_email_auth/tests/models/test_model_functions.py
rest_email_auth/tests/models/test_password_reset_token_model.py
rest_email_auth/tests/serializers/__init__.py
rest_email_auth/tests/serializers/test_email_serializer.py
django_rest_email_auth-5.0.0.dist-info/METADATA
django_rest_email_auth-5.0.0.dist-info/WHEEL
django_rest_email_auth-5.0.0.dist-info/licenses/LICENSE
django_rest_email_auth-5.0.0.dist-info/RECORD
