Metadata-Version: 2.4
Name: django-rest-email-auth
Version: 5.0.0
Summary: Django app for email based authentication and registration via a REST API.
License: MIT
License-File: LICENSE
Author: Chathan Driehuys
Author-email: chathan@driehuys.com
Requires-Python: >=3.9,<4.0
Classifier: License :: OSI Approved :: MIT License
Classifier: Programming Language :: Python :: 3
Classifier: Programming Language :: Python :: 3.9
Classifier: Programming Language :: Python :: 3.10
Classifier: Programming Language :: Python :: 3.11
Classifier: Programming Language :: Python :: 3.12
Classifier: Programming Language :: Python :: 3.13
Classifier: Programming Language :: Python :: 3.14
Requires-Dist: Django (>=4.2,<6)
Requires-Dist: django-email-utils (>=1,<2)
Requires-Dist: djangorestframework (>=3.16,<4.0)
